{
    "0": { "desc": "Entwickler", "is-a": [ 3, 8 ], "can-set": [0] },
    "1": { "desc": "Heimratsmitglied" },
    "2": { "desc": "Stockwerkssprecher", "is-a": [1] },
    "3": { 
        "desc": "Heimratsvorsitz",
        "is-a": [1],
        "can-set": [
            0, 3, 6, 7, 8, 9, 10, 11, 12, 13, 14, 16, 
            1000, 1001, 1002, 1003, 1004, 1005, 1006, 1007, 1008, 1009, 1010, 1011, 1012, 1013, 1014, 1015, 1016, 1017, 1018, 1019,
            2001, 2002, 2003, 2004, 2005, 2006, 2007, 2008,
            2101, 2103, 2105, 2106, 2107, 2108
        ]
    },
    "4": { "desc": "HuTT", "is-a": [1] },
    "5": { "desc": "Haussprecher", "is-a": [4] },
    "6": { "desc": "Tutor", "is-a": [4], "can-set": 5 },
    "7": { "desc": "Haussprecher Hauskasse", "is-a": [5, 2104, 2002], "can-set": [7] },
    "8": { "desc": "Manhattan-Haussprecher", "is-a": [5, 2102], "can-set": [8, 12] },
    "9": { "desc": "Haussprecher Instandhaltung", "is-a": [5], "can-set": [9, 15] },
    "10": { "desc": "Haussprecher Veranstaltung", "is-a": [5], "can-set": [10] },
    "11": { "desc": "Haussprecher Teestube", "is-a": [5], "can-set": [11] },
    "12": { "desc": "Manhattan-Betreiber", "is-a": [1], "can-set": [12] },
    "13": { "desc": "Getränkeverkaufsbetreiber", "is-a": [1], "can-set": [13] },
    "14": { "desc": "Waschmaschinenwart", "is-a": [1], "can-set": [14] },
    "15": { "desc": "Werkzeugkasten-Verleiher", "can-set": [15] },
    "16": { "desc": "Grillwart", "can-set": [16] },
    "17": { "desc": "Nähmaschinenverwalter", "can-set": [17] },
    "18": { "desc": "Stockwerks-Getränkewart" },
    "1000": { "desc": "Stockwerkssprecher Erdgeschoss", "is-a": [2], "can-set": [1000, 1100] },
    "1001": { "desc": "Stockwerkssprecher 1. Stock", "is-a": [2], "can-set": [1001, 1101] },
    "1002": { "desc": "Stockwerkssprecher 2. Stock", "is-a": [2], "can-set": [1002, 1102] },
    "1003": { "desc": "Stockwerkssprecher 3. Stock", "is-a": [2], "can-set": [1003, 1103] },
    "1004": { "desc": "Stockwerkssprecher 4. Stock", "is-a": [2], "can-set": [1004, 1104] },
    "1005": { "desc": "Stockwerkssprecher 5. Stock", "is-a": [2], "can-set": [1005, 1105] },
    "1006": { "desc": "Stockwerkssprecher 6. Stock", "is-a": [2], "can-set": [1006, 1106] },
    "1007": { "desc": "Stockwerkssprecher 7. Stock", "is-a": [2], "can-set": [1007, 1107] },
    "1008": { "desc": "Stockwerkssprecher 8. Stock", "is-a": [2], "can-set": [1008, 1108] },
    "1009": { "desc": "Stockwerkssprecher 9. Stock", "is-a": [2], "can-set": [1009, 1109] },
    "1010": { "desc": "Stockwerkssprecher 10. Stock", "is-a": [2], "can-set": [1010, 1110] },
    "1011": { "desc": "Stockwerkssprecher 11. Stock", "is-a": [2], "can-set": [1011, 1111] },
    "1012": { "desc": "Stockwerkssprecher 12. Stock", "is-a": [2], "can-set": [1012, 1112] },
    "1013": { "desc": "Stockwerkssprecher 13. Stock", "is-a": [2], "can-set": [1013, 1113] },
    "1014": { "desc": "Stockwerkssprecher 14. Stock", "is-a": [2], "can-set": [1014, 1114] },
    "1015": { "desc": "Stockwerkssprecher 15. Stock", "is-a": [2], "can-set": [1015, 1115] },
    "1016": { "desc": "Stockwerkssprecher 16. Stock", "is-a": [2], "can-set": [1016, 1116] },
    "1017": { "desc": "Stockwerkssprecher 17. Stock", "is-a": [2], "can-set": [1017, 1117] },
    "1018": { "desc": "Stockwerkssprecher 18. Stock", "is-a": [2], "can-set": [1018, 1118] },
    "1019": { "desc": "Stockwerkssprecher 19. Stock", "is-a": [2], "can-set": [1019, 1119] },
    "1100": { "desc": "Getränkewart Erdgeschoss", "is-a": [18] },
    "1101": { "desc": "Getränkewart 1. Stock", "is-a": [18] },
    "1102": { "desc": "Getränkewart 2. Stock", "is-a": [18] },
    "1103": { "desc": "Getränkewart 3. Stock", "is-a": [18] },
    "1104": { "desc": "Getränkewart 4. Stock", "is-a": [18] },
    "1105": { "desc": "Getränkewart 5. Stock", "is-a": [18] },
    "1106": { "desc": "Getränkewart 6. Stock", "is-a": [18] },
    "1107": { "desc": "Getränkewart 7. Stock", "is-a": [18] },
    "1108": { "desc": "Getränkewart 8. Stock", "is-a": [18] },
    "1109": { "desc": "Getränkewart 9. Stock", "is-a": [18] },
    "1110": { "desc": "Getränkewart 10. Stock", "is-a": [18] },
    "1111": { "desc": "Getränkewart 11. Stock", "is-a": [18] },
    "1112": { "desc": "Getränkewart 12. Stock", "is-a": [18] },
    "1113": { "desc": "Getränkewart 13. Stock", "is-a": [18] },
    "1114": { "desc": "Getränkewart 14. Stock", "is-a": [18] },
    "1115": { "desc": "Getränkewart 15. Stock", "is-a": [18] },
    "1116": { "desc": "Getränkewart 16. Stock", "is-a": [18] },
    "1117": { "desc": "Getränkewart 17. Stock", "is-a": [18] },
    "1118": { "desc": "Getränkewart 18. Stock", "is-a": [18] },
    "1119": { "desc": "Getränkewart 19. Stock", "is-a": [18] },
    "2000": { "desc": "Ausschussmitglied", "is-a": [1] },
    "2001": { "desc": "Mitglied des Hauskassenprüfungsausschusses", "is-a": [2000] },
    "2002": { "desc": "Mitglied des Manhattanausschusses", "is-a": [2000] },
    "2003": { "desc": "Mitglied des Wahlausschusses", "is-a": [2000] },
    "2004": { "desc": "Mitglied des Getränkeverkaufsausschusses", "is-a": [2000] },
    "2005": { "desc": "Mitglied des Internetausschusses", "is-a": [2000] },
    "2006": { "desc": "Mitglied des Dachterrassenausschusses", "is-a": [2000] },
    "2007": { "desc": "Vertrauensperson", "is-a": [2000] },
    "2008": { "desc": "Haussportverantwortlicher", "is-a": [2000] },
    "2101": { "desc": "Vorsitzender des Hauskassenprüfungsausschusses", "is-a": [2001], "can-set": [2001] },
    "2102": { "desc": "Vorsitzender des Manhattanausschusses", "is-a": [2002], "can-set": [2002] },
    "2103": { "desc": "Vorsitzender des Wahlausschusses", "is-a": [2003], "can-set": [2003] },
    "2104": { "desc": "Vorsitzender des Getränkeverkaufsausschusses", "is-a": [2004], "can-set": [2004] },
    "2105": { "desc": "Vorsitzender des Internetausschusses", "is-a": [2005], "can-set": [2005] },
    "2106": { "desc": "Vorsitzender des Dachterrassenausschusses", "is-a": [2006], "can-set": [2006] },
    "2107": { "desc": "Vorsitzende Vertrauensperson", "is-a": [2007], "can-set": [2007] },
    "2108": { "desc": "Vorsitzender Haussportverantwortlicher", "is-a": [2008], "can-set": [2008] }
}